torchcomp/__init__.py
torchcomp/core.py
torchcomp-0.2.1.dist-info/LICENSE
torchcomp-0.2.1.dist-info/METADATA
torchcomp-0.2.1.dist-info/WHEEL
torchcomp-0.2.1.dist-info/top_level.txt
torchcomp-0.2.1.dist-info/RECORD
