Metadata-Version: 2.1
Name: torchcomp
Version: 0.2.1
Summary: Fast, efficient, and differentiable dynamic range compression/expansion/limiting for PyTorch.
Home-page: https://github.com/yoyololicon/torchcomp
Author: Chin-Yun Yu
Author-email: chin-yun.yu@qmul.ac.uk
Classifier: Programming Language :: Python :: 3
Classifier: License :: OSI Approved :: MIT License
Classifier: Operating System :: OS Independent
License-File: LICENSE
Requires-Dist: torch>=2
Requires-Dist: torchlpc
Requires-Dist: numpy
Requires-Dist: numba
